<?xml version="1.0" ?>
<Employees exportDate="2025-10-19T21:16:40" company="Arrow Limousine &amp; Sedan Ltd.">
  <Employee>
    <Name>Andrew Lafont</Name>
    <TransactionCount>2</TransactionCount>
    <FirstTransaction>2012-02-23</FirstTransaction>
    <LastTransaction>2012-02-23</LastTransaction>
    <TotalDebit>112.96</TotalDebit>
    <TotalCredit>112.96</TotalCredit>
    <Address>See QuickBooks CRA export for contact details</Address>
  </Employee>
  <Employee>
    <Name>Angel Escobar</Name>
    <TransactionCount>32</TransactionCount>
    <FirstTransaction>2012-05-04</FirstTransaction>
    <LastTransaction>2015-09-30</LastTransaction>
    <TotalDebit>9839.25</TotalDebit>
    <TotalCredit>9839.25</TotalCredit>
    <Address>See QuickBooks CRA export for contact details</Address>
  </Employee>
  <Employee>
    <Name>Barny Forsberg</Name>
    <TransactionCount>6</TransactionCount>
    <FirstTransaction>2012-04-05</FirstTransaction>
    <LastTransaction>2012-06-11</LastTransaction>
    <TotalDebit>543.72</TotalDebit>
    <TotalCredit>543.72</TotalCredit>
    <Address>See QuickBooks CRA export for contact details</Address>
  </Employee>
  <Employee>
    <Name>Brian Sherrard (deleted)</Name>
    <TransactionCount>2</TransactionCount>
    <FirstTransaction>2014-06-03</FirstTransaction>
    <LastTransaction>2014-06-03</LastTransaction>
    <TotalDebit>1406.59</TotalDebit>
    <TotalCredit>1406.59</TotalCredit>
    <Address>See QuickBooks CRA export for contact details</Address>
  </Employee>
  <Employee>
    <Name>Brittinee Hills</Name>
    <TransactionCount>28</TransactionCount>
    <FirstTransaction>2015-09-30</FirstTransaction>
    <LastTransaction>2015-11-30</LastTransaction>
    <TotalDebit>1073.94</TotalDebit>
    <TotalCredit>1073.94</TotalCredit>
    <Address>See QuickBooks CRA export for contact details</Address>
  </Employee>
  <Employee>
    <Name>Bryan Ryder</Name>
    <TransactionCount>20</TransactionCount>
    <FirstTransaction>2015-05-31</FirstTransaction>
    <LastTransaction>2015-06-30</LastTransaction>
    <TotalDebit>525.69</TotalDebit>
    <TotalCredit>525.69</TotalCredit>
    <Address>See QuickBooks CRA export for contact details</Address>
  </Employee>
  <Employee>
    <Name>Cassidy Piesse</Name>
    <TransactionCount>24</TransactionCount>
    <FirstTransaction>2015-01-31</FirstTransaction>
    <LastTransaction>2015-05-31</LastTransaction>
    <TotalDebit>709.47</TotalDebit>
    <TotalCredit>709.47</TotalCredit>
    <Address>See QuickBooks CRA export for contact details</Address>
  </Employee>
  <Employee>
    <Name>Chantal Thomas</Name>
    <TransactionCount>6</TransactionCount>
    <FirstTransaction>2012-09-25</FirstTransaction>
    <LastTransaction>2012-12-03</LastTransaction>
    <TotalDebit>2360.98</TotalDebit>
    <TotalCredit>2360.98</TotalCredit>
    <Address>See QuickBooks CRA export for contact details</Address>
  </Employee>
  <Employee>
    <Name>Clint Allen</Name>
    <TransactionCount>23</TransactionCount>
    <FirstTransaction>2015-11-30</FirstTransaction>
    <LastTransaction>2016-01-15</LastTransaction>
    <TotalDebit>2179.40</TotalDebit>
    <TotalCredit>2179.40</TotalCredit>
    <Address>See QuickBooks CRA export for contact details</Address>
  </Employee>
  <Employee>
    <Name>Dale Mernard</Name>
    <TransactionCount>18</TransactionCount>
    <FirstTransaction>2012-07-17</FirstTransaction>
    <LastTransaction>2013-05-23</LastTransaction>
    <TotalDebit>5049.32</TotalDebit>
    <TotalCredit>5049.32</TotalCredit>
    <Address>See QuickBooks CRA export for contact details</Address>
  </Employee>
  <Employee>
    <Name>David W Richard</Name>
    <TransactionCount>46</TransactionCount>
    <FirstTransaction>2015-01-28</FirstTransaction>
    <LastTransaction>2016-03-23</LastTransaction>
    <TotalDebit>14623.20</TotalDebit>
    <TotalCredit>14623.20</TotalCredit>
    <Address>See QuickBooks CRA export for contact details</Address>
  </Employee>
  <Employee>
    <Name>Don Malcomson</Name>
    <TransactionCount>4</TransactionCount>
    <FirstTransaction>2014-04-04</FirstTransaction>
    <LastTransaction>2014-05-05</LastTransaction>
    <TotalDebit>699.31</TotalDebit>
    <TotalCredit>699.31</TotalCredit>
    <Address>See QuickBooks CRA export for contact details</Address>
  </Employee>
  <Employee>
    <Name>Douglas Redmond</Name>
    <TransactionCount>43</TransactionCount>
    <FirstTransaction>2012-06-06</FirstTransaction>
    <LastTransaction>2015-01-31</LastTransaction>
    <TotalDebit>31474.05</TotalDebit>
    <TotalCredit>31474.05</TotalCredit>
    <Address>See QuickBooks CRA export for contact details</Address>
  </Employee>
  <Employee>
    <Name>Dustan Townsend</Name>
    <TransactionCount>8</TransactionCount>
    <FirstTransaction>2012-10-01</FirstTransaction>
    <LastTransaction>2012-12-03</LastTransaction>
    <TotalDebit>2384.45</TotalDebit>
    <TotalCredit>2384.45</TotalCredit>
    <Address>See QuickBooks CRA export for contact details</Address>
  </Employee>
  <Employee>
    <Name>Erik Richard</Name>
    <TransactionCount>2</TransactionCount>
    <FirstTransaction>2012-04-11</FirstTransaction>
    <LastTransaction>2012-04-11</LastTransaction>
    <TotalDebit>500.00</TotalDebit>
    <TotalCredit>500.00</TotalCredit>
    <Address>See QuickBooks CRA export for contact details</Address>
  </Employee>
  <Employee>
    <Name>Gerald Skanderup</Name>
    <TransactionCount>161</TransactionCount>
    <FirstTransaction>2014-03-05</FirstTransaction>
    <LastTransaction>2016-01-15</LastTransaction>
    <TotalDebit>29537.09</TotalDebit>
    <TotalCredit>29537.09</TotalCredit>
    <Address>See QuickBooks CRA export for contact details</Address>
  </Employee>
  <Employee>
    <Name>Ginie Sanderson</Name>
    <TransactionCount>9</TransactionCount>
    <FirstTransaction>2015-01-31</FirstTransaction>
    <LastTransaction>2015-01-31</LastTransaction>
    <TotalDebit>81.94</TotalDebit>
    <TotalCredit>81.94</TotalCredit>
    <Address>See QuickBooks CRA export for contact details</Address>
  </Employee>
  <Employee>
    <Name>Gordon Peterson</Name>
    <TransactionCount>51</TransactionCount>
    <FirstTransaction>2015-01-31</FirstTransaction>
    <LastTransaction>2015-06-30</LastTransaction>
    <TotalDebit>1054.26</TotalDebit>
    <TotalCredit>1054.26</TotalCredit>
    <Address>See QuickBooks CRA export for contact details</Address>
  </Employee>
  <Employee>
    <Name>Heather Gullison</Name>
    <TransactionCount>2</TransactionCount>
    <FirstTransaction>2012-03-08</FirstTransaction>
    <LastTransaction>2012-03-08</LastTransaction>
    <TotalDebit>214.56</TotalDebit>
    <TotalCredit>214.56</TotalCredit>
    <Address>See QuickBooks CRA export for contact details</Address>
  </Employee>
  <Employee>
    <Name>James Ross</Name>
    <TransactionCount>2</TransactionCount>
    <FirstTransaction>2013-11-01</FirstTransaction>
    <LastTransaction>2013-11-01</LastTransaction>
    <TotalDebit>531.62</TotalDebit>
    <TotalCredit>531.62</TotalCredit>
    <Address>See QuickBooks CRA export for contact details</Address>
  </Employee>
  <Employee>
    <Name>Jeannie Shillington</Name>
    <TransactionCount>205</TransactionCount>
    <FirstTransaction>2012-01-09</FirstTransaction>
    <LastTransaction>2016-01-15</LastTransaction>
    <TotalDebit>58879.11</TotalDebit>
    <TotalCredit>58879.11</TotalCredit>
    <Address>See QuickBooks CRA export for contact details</Address>
  </Employee>
  <Employee>
    <Name>Jeff Brill</Name>
    <TransactionCount>6</TransactionCount>
    <FirstTransaction>2013-11-01</FirstTransaction>
    <LastTransaction>2013-12-31</LastTransaction>
    <TotalDebit>1053.52</TotalDebit>
    <TotalCredit>1053.52</TotalCredit>
    <Address>See QuickBooks CRA export for contact details</Address>
  </Employee>
  <Employee>
    <Name>Jesse Gordon</Name>
    <TransactionCount>115</TransactionCount>
    <FirstTransaction>2012-05-30</FirstTransaction>
    <LastTransaction>2015-07-21</LastTransaction>
    <TotalDebit>41492.43</TotalDebit>
    <TotalCredit>41492.43</TotalCredit>
    <Address>See QuickBooks CRA export for contact details</Address>
  </Employee>
  <Employee>
    <Name>Joel Nelson</Name>
    <TransactionCount>2</TransactionCount>
    <FirstTransaction>2012-04-18</FirstTransaction>
    <LastTransaction>2012-04-18</LastTransaction>
    <TotalDebit>2191.47</TotalDebit>
    <TotalCredit>2191.47</TotalCredit>
    <Address>See QuickBooks CRA export for contact details</Address>
  </Employee>
  <Employee>
    <Name>John Sheldon</Name>
    <TransactionCount>27</TransactionCount>
    <FirstTransaction>2015-02-28</FirstTransaction>
    <LastTransaction>2015-06-30</LastTransaction>
    <TotalDebit>1106.15</TotalDebit>
    <TotalCredit>1106.15</TotalCredit>
    <Address>See QuickBooks CRA export for contact details</Address>
  </Employee>
  <Employee>
    <Name>Jonathan Korsh</Name>
    <TransactionCount>8</TransactionCount>
    <FirstTransaction>2013-12-04</FirstTransaction>
    <LastTransaction>2014-02-05</LastTransaction>
    <TotalDebit>4621.52</TotalDebit>
    <TotalCredit>4621.52</TotalCredit>
    <Address>See QuickBooks CRA export for contact details</Address>
  </Employee>
  <Employee>
    <Name>Jordan Schidlowsky</Name>
    <TransactionCount>49</TransactionCount>
    <FirstTransaction>2015-06-30</FirstTransaction>
    <LastTransaction>2015-11-30</LastTransaction>
    <TotalDebit>1184.49</TotalDebit>
    <TotalCredit>1184.49</TotalCredit>
    <Address>See QuickBooks CRA export for contact details</Address>
  </Employee>
  <Employee>
    <Name>Jose Fajordo</Name>
    <TransactionCount>81</TransactionCount>
    <FirstTransaction>2015-06-30</FirstTransaction>
    <LastTransaction>2016-01-15</LastTransaction>
    <TotalDebit>6820.97</TotalDebit>
    <TotalCredit>6820.97</TotalCredit>
    <Address>See QuickBooks CRA export for contact details</Address>
  </Employee>
  <Employee>
    <Name>Josh Lycklamon (deleted)</Name>
    <TransactionCount>2</TransactionCount>
    <FirstTransaction>2014-03-10</FirstTransaction>
    <LastTransaction>2014-03-10</LastTransaction>
    <TotalDebit>700.00</TotalDebit>
    <TotalCredit>700.00</TotalCredit>
    <Address>See QuickBooks CRA export for contact details</Address>
  </Employee>
  <Employee>
    <Name>Karen. Richard</Name>
    <TransactionCount>12</TransactionCount>
    <FirstTransaction>2012-04-12</FirstTransaction>
    <LastTransaction>2014-05-30</LastTransaction>
    <TotalDebit>12800.00</TotalDebit>
    <TotalCredit>12800.00</TotalCredit>
    <Address>See QuickBooks CRA export for contact details</Address>
  </Employee>
  <Employee>
    <Name>Keith Dixon</Name>
    <TransactionCount>52</TransactionCount>
    <FirstTransaction>2014-05-11</FirstTransaction>
    <LastTransaction>2015-09-21</LastTransaction>
    <TotalDebit>12788.32</TotalDebit>
    <TotalCredit>13094.32</TotalCredit>
    <Address>See QuickBooks CRA export for contact details</Address>
  </Employee>
  <Employee>
    <Name>Kerri Bently</Name>
    <TransactionCount>2</TransactionCount>
    <FirstTransaction>2014-02-24</FirstTransaction>
    <LastTransaction>2014-02-24</LastTransaction>
    <TotalDebit>261.2</TotalDebit>
    <TotalCredit>261.2</TotalCredit>
    <Address>See QuickBooks CRA export for contact details</Address>
  </Employee>
  <Employee>
    <Name>Kevin Boulley</Name>
    <TransactionCount>18</TransactionCount>
    <FirstTransaction>2012-11-08</FirstTransaction>
    <LastTransaction>2013-09-30</LastTransaction>
    <TotalDebit>5081.29</TotalDebit>
    <TotalCredit>5081.29</TotalCredit>
    <Address>See QuickBooks CRA export for contact details</Address>
  </Employee>
  <Employee>
    <Name>Kyle Maier</Name>
    <TransactionCount>123</TransactionCount>
    <FirstTransaction>2015-01-31</FirstTransaction>
    <LastTransaction>2016-01-15</LastTransaction>
    <TotalDebit>5681.57</TotalDebit>
    <TotalCredit>5681.57</TotalCredit>
    <Address>See QuickBooks CRA export for contact details</Address>
  </Employee>
  <Employee>
    <Name>Kyle Martens</Name>
    <TransactionCount>34</TransactionCount>
    <FirstTransaction>2015-01-31</FirstTransaction>
    <LastTransaction>2015-03-31</LastTransaction>
    <TotalDebit>2034.39</TotalDebit>
    <TotalCredit>2034.39</TotalCredit>
    <Address>See QuickBooks CRA export for contact details</Address>
  </Employee>
  <Employee>
    <Name>Larry Taylor</Name>
    <TransactionCount>91</TransactionCount>
    <FirstTransaction>2013-07-08</FirstTransaction>
    <LastTransaction>2015-09-30</LastTransaction>
    <TotalDebit>11215.30</TotalDebit>
    <TotalCredit>11215.30</TotalCredit>
    <Address>See QuickBooks CRA export for contact details</Address>
  </Employee>
  <Employee>
    <Name>Len Whitney</Name>
    <TransactionCount>33</TransactionCount>
    <FirstTransaction>2015-07-31</FirstTransaction>
    <LastTransaction>2015-09-30</LastTransaction>
    <TotalDebit>2920.30</TotalDebit>
    <TotalCredit>2920.30</TotalCredit>
    <Address>See QuickBooks CRA export for contact details</Address>
  </Employee>
  <Employee>
    <Name>Logan Mosinsky</Name>
    <TransactionCount>6</TransactionCount>
    <FirstTransaction>2012-10-09</FirstTransaction>
    <LastTransaction>2013-10-07</LastTransaction>
    <TotalDebit>643.52</TotalDebit>
    <TotalCredit>643.52</TotalCredit>
    <Address>See QuickBooks CRA export for contact details</Address>
  </Employee>
  <Employee>
    <Name>Madeleine Escobar</Name>
    <TransactionCount>56</TransactionCount>
    <FirstTransaction>2015-07-31</FirstTransaction>
    <LastTransaction>2016-01-15</LastTransaction>
    <TotalDebit>3141.06</TotalDebit>
    <TotalCredit>3141.06</TotalCredit>
    <Address>See QuickBooks CRA export for contact details</Address>
  </Employee>
  <Employee>
    <Name>Marc A Cote</Name>
    <TransactionCount>16</TransactionCount>
    <FirstTransaction>2013-06-05</FirstTransaction>
    <LastTransaction>2014-03-24</LastTransaction>
    <TotalDebit>3664.18</TotalDebit>
    <TotalCredit>3664.18</TotalCredit>
    <Address>See QuickBooks CRA export for contact details</Address>
  </Employee>
  <Employee>
    <Name>Mark Linton</Name>
    <TransactionCount>23</TransactionCount>
    <FirstTransaction>2012-04-16</FirstTransaction>
    <LastTransaction>2015-09-30</LastTransaction>
    <TotalDebit>8536.70</TotalDebit>
    <TotalCredit>8536.70</TotalCredit>
    <Address>See QuickBooks CRA export for contact details</Address>
  </Employee>
  <Employee>
    <Name>Matt Kapustinsky</Name>
    <TransactionCount>11</TransactionCount>
    <FirstTransaction>2015-07-31</FirstTransaction>
    <LastTransaction>2015-07-31</LastTransaction>
    <TotalDebit>476.52</TotalDebit>
    <TotalCredit>476.52</TotalCredit>
    <Address>See QuickBooks CRA export for contact details</Address>
  </Employee>
  <Employee>
    <Name>Michael Richard</Name>
    <TransactionCount>342</TransactionCount>
    <FirstTransaction>2012-01-04</FirstTransaction>
    <LastTransaction>2025-08-19</LastTransaction>
    <TotalDebit>86888.01</TotalDebit>
    <TotalCredit>86888.01</TotalCredit>
    <Address>See QuickBooks CRA export for contact details</Address>
  </Employee>
  <Employee>
    <Name>Norman Therrien</Name>
    <TransactionCount>124</TransactionCount>
    <FirstTransaction>2013-12-31</FirstTransaction>
    <LastTransaction>2016-01-15</LastTransaction>
    <TotalDebit>10047.51</TotalDebit>
    <TotalCredit>10047.51</TotalCredit>
    <Address>See QuickBooks CRA export for contact details</Address>
  </Employee>
  <Employee>
    <Name>Pat Fraser</Name>
    <TransactionCount>8</TransactionCount>
    <FirstTransaction>2013-04-19</FirstTransaction>
    <LastTransaction>2013-12-31</LastTransaction>
    <TotalDebit>1118.57</TotalDebit>
    <TotalCredit>1118.57</TotalCredit>
    <Address>See QuickBooks CRA export for contact details</Address>
  </Employee>
  <Employee>
    <Name>Paul D Richard</Name>
    <TransactionCount>129</TransactionCount>
    <FirstTransaction>2012-07-04</FirstTransaction>
    <LastTransaction>2016-01-15</LastTransaction>
    <TotalDebit>30699.30</TotalDebit>
    <TotalCredit>30699.30</TotalCredit>
    <Address>See QuickBooks CRA export for contact details</Address>
  </Employee>
  <Employee>
    <Name>Paul Mansell</Name>
    <TransactionCount>113</TransactionCount>
    <FirstTransaction>2012-01-05</FirstTransaction>
    <LastTransaction>2015-04-30</LastTransaction>
    <TotalDebit>44385.10</TotalDebit>
    <TotalCredit>44385.10</TotalCredit>
    <Address>See QuickBooks CRA export for contact details</Address>
  </Employee>
  <Employee>
    <Name>Shawn Collen</Name>
    <TransactionCount>4</TransactionCount>
    <FirstTransaction>2014-05-14</FirstTransaction>
    <LastTransaction>2014-05-29</LastTransaction>
    <TotalDebit>723.87</TotalDebit>
    <TotalCredit>723.87</TotalCredit>
    <Address>See QuickBooks CRA export for contact details</Address>
  </Employee>
  <Employee>
    <Name>Shondal Saunders</Name>
    <TransactionCount>74</TransactionCount>
    <FirstTransaction>2015-02-28</FirstTransaction>
    <LastTransaction>2015-08-31</LastTransaction>
    <TotalDebit>4023.67</TotalDebit>
    <TotalCredit>4023.67</TotalCredit>
    <Address>See QuickBooks CRA export for contact details</Address>
  </Employee>
  <Employee>
    <Name>Stephen Meek</Name>
    <TransactionCount>14</TransactionCount>
    <FirstTransaction>2013-10-07</FirstTransaction>
    <LastTransaction>2014-03-21</LastTransaction>
    <TotalDebit>13762.01</TotalDebit>
    <TotalCredit>13762.01</TotalCredit>
    <Address>See QuickBooks CRA export for contact details</Address>
  </Employee>
  <Employee>
    <Name>Tammy Pettitt</Name>
    <TransactionCount>146</TransactionCount>
    <FirstTransaction>2013-11-01</FirstTransaction>
    <LastTransaction>2016-01-15</LastTransaction>
    <TotalDebit>39586.84</TotalDebit>
    <TotalCredit>39586.84</TotalCredit>
    <Address>See QuickBooks CRA export for contact details</Address>
  </Employee>
  <Employee>
    <Name>Terry Donaldson</Name>
    <TransactionCount>22</TransactionCount>
    <FirstTransaction>2015-11-30</FirstTransaction>
    <LastTransaction>2016-01-15</LastTransaction>
    <TotalDebit>2144.07</TotalDebit>
    <TotalCredit>2144.07</TotalCredit>
    <Address>See QuickBooks CRA export for contact details</Address>
  </Employee>
  <Employee>
    <Name>Victor Youngman</Name>
    <TransactionCount>92</TransactionCount>
    <FirstTransaction>2015-06-30</FirstTransaction>
    <LastTransaction>2016-01-15</LastTransaction>
    <TotalDebit>19048.34</TotalDebit>
    <TotalCredit>19048.34</TotalCredit>
    <Address>See QuickBooks CRA export for contact details</Address>
  </Employee>
  <Employee>
    <Name>Wes Charles</Name>
    <TransactionCount>4</TransactionCount>
    <FirstTransaction>2012-04-03</FirstTransaction>
    <LastTransaction>2012-04-25</LastTransaction>
    <TotalDebit>1273.21</TotalDebit>
    <TotalCredit>1273.21</TotalCredit>
    <Address>See QuickBooks CRA export for contact details</Address>
  </Employee>
  <Employee>
    <Name>Zak Keller</Name>
    <TransactionCount>2</TransactionCount>
    <FirstTransaction>2012-08-01</FirstTransaction>
    <LastTransaction>2012-08-01</LastTransaction>
    <TotalDebit>599.06</TotalDebit>
    <TotalCredit>599.06</TotalCredit>
    <Address>See QuickBooks CRA export for contact details</Address>
  </Employee>
</Employees>
